kinbaku/__init__.py
kinbaku/exception.py
kinbaku/graph.py
kinbaku/structure.py
kinbaku/utils.py
kinbaku-0.0.2.dist-info/METADATA
kinbaku-0.0.2.dist-info/WHEEL
kinbaku-0.0.2.dist-info/top_level.txt
kinbaku-0.0.2.dist-info/RECORD
