Metadata-Version: 2.1
Name: kinbaku
Version: 0.0.2
Summary: Efficient graph database on disk
Home-page: https://github.com/kerighan/kinbaku
Author: Maixent Chenebaux
Author-email: max.chbx@gmail.com
License: UNKNOWN
Platform: UNKNOWN
Classifier: Intended Audience :: Developers
Classifier: Programming Language :: Python :: 3
Classifier: License :: OSI Approved :: MIT License
Classifier: Operating System :: OS Independent
Classifier: Topic :: Software Development :: Libraries :: Python Modules
Classifier: Topic :: Database
Requires-Python: >=3.7
Requires-Dist: cachetools
